{
  "schemaVersion": 1,
  "description": "Abstract interface tones for HearthCode. These govern shell ink hierarchy, on-accent contrast, and navigation fills before any platform token mapping.",
  "interfaces": {
    "shellInk": {
      "description": "Primary readable ink for active tabs, fields, and shell labels.",
      "source": {
        "type": "literal",
        "values": {
          "dark": "#d3c9b8",
          "darkSoft": "#cec5ba",
          "light": "#352b21",
          "lightSoft": "#4c463d"
        }
      }
    },
    "supportInk": {
      "description": "Readable supporting shell ink for unfocused active items and general navigation copy.",
      "source": {
        "type": "interface",
        "id": "shellInk"
      },
      "derive": {
        "mix": {
          "with": {
            "type": "surface",
            "id": "sidebar"
          },
          "tFromVariantKnob": "interfaceMix.supportInk"
        }
      }
    },
    "mutedInk": {
      "description": "Secondary shell ink for inactive tabs, section titles, and quiet chrome labels.",
      "source": {
        "type": "interface",
        "id": "shellInk"
      },
      "derive": {
        "mix": {
          "with": {
            "type": "surface",
            "id": "sidebar"
          },
          "tFromVariantKnob": "interfaceMix.mutedInk"
        }
      }
    },
    "subtleInk": {
      "description": "Dormant shell ink for placeholders and inactive iconography.",
      "source": {
        "type": "interface",
        "id": "mutedInk"
      },
      "derive": {
        "mix": {
          "with": {
            "type": "surface",
            "id": "sidebar"
          },
          "tFromVariantKnob": "interfaceMix.subtleInk"
        }
      }
    },
    "onAccentInk": {
      "description": "Readable inverse ink placed on accent and badge fills.",
      "source": {
        "type": "literal",
        "values": {
          "dark": "#161411",
          "darkSoft": "#1b1713",
          "light": "#faf5ef",
          "lightSoft": "#f5efe8"
        }
      }
    },
    "shellRaised": {
      "description": "Raised shell substrate for secondary buttons and bounded form controls.",
      "source": {
        "type": "surface",
        "id": "sidebar"
      },
      "derive": {
        "mix": {
          "with": {
            "type": "interface",
            "id": "shellInk"
          },
          "tFromVariantKnob": "interfaceMix.shellRaised"
        }
      }
    },
    "navActiveFill": {
      "description": "Selected navigation fill for active lists and focused rows.",
      "source": {
        "type": "surface",
        "id": "sidebar"
      },
      "derive": {
        "mix": {
          "with": {
            "type": "interface",
            "id": "shellInk"
          },
          "tFromVariantKnob": "interfaceMix.navActiveFill"
        }
      }
    },
    "navInactiveFill": {
      "description": "Softer navigation fill for inactive selection states and supporting hover groups.",
      "source": {
        "type": "surface",
        "id": "sidebar"
      },
      "derive": {
        "mix": {
          "with": {
            "type": "interface",
            "id": "shellInk"
          },
          "tFromVariantKnob": "interfaceMix.navInactiveFill"
        }
      }
    },
    "shellBand": {
      "description": "Intermediate shell band for section headers and grouped chrome strata.",
      "source": {
        "type": "foundation",
        "family": "shell",
        "tone": "lift"
      }
    },
    "accentHoverFill": {
      "description": "Hover-stage accent fill for buttons and raised controls.",
      "source": {
        "type": "literal",
        "values": {
          "dark": "#d08a4c",
          "darkSoft": "#b98858",
          "light": "#6d838d",
          "lightSoft": "#75878c"
        }
      }
    },
    "onStatusInk": {
      "description": "Readable ink placed on persistent status surfaces.",
      "source": {
        "type": "literal",
        "values": {
          "dark": "#f2e7d1",
          "darkSoft": "#eee2cd",
          "light": "#f6eee3",
          "lightSoft": "#ece3d8"
        }
      }
    },
    "navActiveInk": {
      "description": "Readable ink placed on active navigation fills.",
      "source": {
        "type": "literal",
        "values": {
          "dark": "#e8ddca",
          "darkSoft": "#dfd2be",
          "light": "#352b21",
          "lightSoft": "#4c463d"
        }
      }
    }
  }
}
