{
    "name": "Moss Light",
    "type": "light",
    "colors": {
        "editor.background": "#eee6d8",
        "editor.foreground": "#392f29",
        "editor.lineHighlightBackground": "#d8d0c4",
        "editor.selectionBackground": "#b8791120",
        "editor.selectionHighlightBackground": "#b8791110",
        "editor.wordHighlightBackground": "#b8791114",
        "editor.findMatchBackground": "#b8791136",
        "editor.findMatchHighlightBackground": "#b879111a",
        "editorLineNumber.foreground": "#ada499",
        "editorLineNumber.activeForeground": "#7c5f34",
        "editorCursor.foreground": "#62836c",
        "editorCursor.background": "#eee6d8",
        "editorWhitespace.foreground": "#cfc6b9",
        "editorIndentGuide.background1": "#cfc6b9",
        "editorIndentGuide.activeBackground1": "#8b7d63",
        "editorBracketMatch.background": "#87671814",
        "editorBracketMatch.border": "#8767183d",
        "editorBracketHighlight.foreground1": "#876718",
        "editorBracketHighlight.foreground2": "#b17818",
        "editorBracketHighlight.foreground3": "#257493",
        "editorError.foreground": "#876718",
        "editorWarning.foreground": "#b17818",
        "editorInfo.foreground": "#257493",
        "sideBar.background": "#dbd1c3",
        "sideBar.foreground": "#4c423b",
        "sideBar.border": "#cac1b5",
        "sideBarTitle.foreground": "#6a6057",
        "sideBarSectionHeader.background": "#d0c6b8",
        "sideBarSectionHeader.foreground": "#6a6057",
        "sideBarSectionHeader.border": "#cac1b5",
        "activityBar.background": "#dbd1c3",
        "activityBar.foreground": "#392f29",
        "activityBar.inactiveForeground": "#857b71",
        "activityBar.border": "#cac1b5",
        "activityBarBadge.background": "#b87911",
        "activityBarBadge.foreground": "#f7f1e8",
        "statusBar.background": "#a36e0d",
        "statusBar.foreground": "#f6efe5",
        "statusBar.border": "#cac1b5",
        "statusBar.noFolderBackground": "#8a562d",
        "statusBar.debuggingBackground": "#7f4313",
        "statusBarItem.hoverBackground": "#b8791126",
        "statusBarItem.activeBackground": "#b8791133",
        "titleBar.activeBackground": "#dbd1c3",
        "titleBar.activeForeground": "#392f29",
        "titleBar.inactiveBackground": "#dbd1c3",
        "titleBar.inactiveForeground": "#6a6057",
        "titleBar.border": "#cac1b5",
        "tab.activeBackground": "#eee6d8",
        "tab.activeForeground": "#392f29",
        "tab.activeBorder": "#b87911",
        "tab.inactiveBackground": "#dbd1c3",
        "tab.inactiveForeground": "#6a6057",
        "tab.border": "#cac1b5",
        "tab.hoverBackground": "#d3c9b9",
        "tab.unfocusedActiveForeground": "#4c423b",
        "editorGroupHeader.tabsBackground": "#dbd1c3",
        "editorGroupHeader.tabsBorder": "#cac1b5",
        "panel.background": "#dbd1c3",
        "panel.border": "#cac1b5",
        "panelTitle.activeBorder": "#b87911",
        "panelTitle.activeForeground": "#392f29",
        "panelTitle.inactiveForeground": "#6a6057",
        "terminal.background": "#eee6d8",
        "terminal.foreground": "#392f29",
        "terminal.ansiBlack": "#3a342e",
        "terminal.ansiRed": "#ba5146",
        "terminal.ansiGreen": "#718246",
        "terminal.ansiYellow": "#9d7124",
        "terminal.ansiBlue": "#517d76",
        "terminal.ansiMagenta": "#a26179",
        "terminal.ansiCyan": "#608763",
        "terminal.ansiWhite": "#43382e",
        "terminal.ansiBrightBlack": "#8c7c69",
        "terminal.ansiBrightRed": "#c9675c",
        "terminal.ansiBrightGreen": "#79914c",
        "terminal.ansiBrightYellow": "#ab8034",
        "terminal.ansiBrightBlue": "#658d85",
        "terminal.ansiBrightMagenta": "#b9758b",
        "terminal.ansiBrightCyan": "#70946f",
        "terminal.ansiBrightWhite": "#2d241e",
        "terminalCursor.foreground": "#62836c",
        "input.background": "#d9d0c3",
        "input.foreground": "#392f29",
        "input.border": "#c4baad",
        "input.placeholderForeground": "#857b71",
        "inputOption.activeBorder": "#b87911",
        "inputOption.activeBackground": "#b879110f",
        "dropdown.background": "#d9d0c3",
        "dropdown.foreground": "#392f29",
        "dropdown.border": "#c4baad",
        "button.background": "#b87911",
        "button.foreground": "#f7f1e8",
        "button.hoverBackground": "#bb7e16",
        "button.secondaryBackground": "#c4baad",
        "button.secondaryForeground": "#392f29",
        "list.activeSelectionBackground": "#c4baad",
        "list.activeSelectionForeground": "#2f2822",
        "list.hoverBackground": "#d3c9b9",
        "list.hoverForeground": "#392f29",
        "list.inactiveSelectionBackground": "#cec4b7",
        "list.highlightForeground": "#b87911",
        "list.focusBackground": "#c4baad",
        "scrollbarSlider.background": "#d2c2a566",
        "scrollbarSlider.hoverBackground": "#d2c2a599",
        "scrollbarSlider.activeBackground": "#b49d7baa",
        "badge.background": "#b87911",
        "badge.foreground": "#f7f1e8",
        "progressBar.background": "#b87911",
        "focusBorder": "#b8791138",
        "selection.background": "#b8791120",
        "widget.shadow": "#00000033",
        "notifications.background": "#d9d0c3",
        "notifications.foreground": "#392f29",
        "notifications.border": "#c4baad",
        "notificationLink.foreground": "#b87911",
        "gitDecoration.addedResourceForeground": "#307424",
        "gitDecoration.modifiedResourceForeground": "#b17818",
        "gitDecoration.deletedResourceForeground": "#876718",
        "gitDecoration.untrackedResourceForeground": "#307424",
        "gitDecoration.ignoredResourceForeground": "#857b71",
        "gitDecoration.conflictingResourceForeground": "#876718"
    },
    "tokenColors": [
        {
            "scope": [
                "comment",
                "punctuation.definition.comment"
            ],
            "settings": {
                "foreground": "#776c61",
                "fontStyle": "italic"
            }
        },
        {
            "scope": [
                "keyword",
                "storage.type",
                "storage.modifier",
                "keyword.control"
            ],
            "settings": {
                "foreground": "#876718",
                "fontStyle": "bold"
            }
        },
        {
            "scope": [
                "keyword.operator",
                "keyword.operator.assignment"
            ],
            "settings": {
                "foreground": "#66615b",
                "fontStyle": ""
            }
        },
        {
            "scope": [
                "meta.function-call entity.name.function",
                "meta.function-call.js entity.name.function.js",
                "meta.function-call.ts entity.name.function.ts",
                "meta.function-call.py entity.name.function.py",
                "meta.function-call.python entity.name.function.python",
                "meta.function-call.go entity.name.function.go",
                "meta.function-call.rust entity.name.function.rust"
            ],
            "settings": {
                "foreground": "#317425"
            }
        },
        {
            "scope": [
                "meta.method-call entity.name.function",
                "meta.method-call.js entity.name.function.js",
                "meta.method-call.ts entity.name.function.ts",
                "meta.method-call.py entity.name.function.py",
                "meta.method-call.python entity.name.function.python",
                "meta.method-call.go entity.name.function.go",
                "meta.method-call.rust entity.name.function.rust"
            ],
            "settings": {
                "foreground": "#5c752d"
            }
        },
        {
            "scope": [
                "entity.name.function",
                "support.function",
                "meta.function-call.generic"
            ],
            "settings": {
                "foreground": "#317425"
            }
        },
        {
            "scope": [
                "entity.name.function.member",
                "entity.name.function.member.python",
                "entity.name.function.member.go",
                "entity.name.function.member.rust"
            ],
            "settings": {
                "foreground": "#5c752d"
            }
        },
        {
            "scope": [
                "variable.other.property",
                "variable.other.member",
                "meta.property-name",
                "support.type.property-name"
            ],
            "settings": {
                "foreground": "#465f45"
            }
        },
        {
            "scope": [
                "string",
                "string.quoted",
                "string.template",
                "string.regexp"
            ],
            "settings": {
                "foreground": "#756733"
            }
        },
        {
            "scope": [
                "constant.numeric",
                "constant.language.boolean",
                "constant.language.null",
                "constant.language.undefined"
            ],
            "settings": {
                "foreground": "#3f6ea7"
            }
        },
        {
            "scope": [
                "entity.name.type",
                "entity.name.class",
                "storage.type.java",
                "storage.type.primitive.java",
                "entity.name.struct.rust",
                "entity.name.type.class",
                "support.type",
                "support.type.builtin",
                "support.class"
            ],
            "settings": {
                "foreground": "#257493",
                "fontStyle": "italic"
            }
        },
        {
            "scope": [
                "variable",
                "variable.other.readwrite",
                "variable.other.constant"
            ],
            "settings": {
                "foreground": "#433e38"
            }
        },
        {
            "scope": [
                "meta.object-literal.key"
            ],
            "settings": {
                "foreground": "#854416"
            }
        },
        {
            "scope": [
                "entity.other.attribute-name"
            ],
            "settings": {
                "foreground": "#0067cc"
            }
        },
        {
            "scope": [
                "entity.name.tag",
                "punctuation.definition.tag"
            ],
            "settings": {
                "foreground": "#7f7d2e"
            }
        },
        {
            "scope": [
                "meta.decorator",
                "punctuation.decorator"
            ],
            "settings": {
                "foreground": "#8f4c00",
                "fontStyle": "italic"
            }
        },
        {
            "scope": [
                "punctuation",
                "meta.brace"
            ],
            "settings": {
                "foreground": "#9c805a"
            }
        },
        {
            "scope": [
                "constant.other.color",
                "support.constant"
            ],
            "settings": {
                "foreground": "#3f6ea7"
            }
        },
        {
            "scope": [
                "markup.heading"
            ],
            "settings": {
                "foreground": "#7b4500",
                "fontStyle": "bold"
            }
        },
        {
            "scope": [
                "markup.bold"
            ],
            "settings": {
                "foreground": "#a4251b",
                "fontStyle": "bold"
            }
        },
        {
            "scope": [
                "markup.italic"
            ],
            "settings": {
                "foreground": "#964a00",
                "fontStyle": "italic"
            }
        },
        {
            "scope": [
                "markup.inline.raw",
                "markup.fenced_code"
            ],
            "settings": {
                "foreground": "#007500"
            }
        },
        {
            "scope": [
                "markup.underline.link"
            ],
            "settings": {
                "foreground": "#007500"
            }
        },
        {
            "scope": [
                "invalid.deprecated"
            ],
            "settings": {
                "foreground": "#b92e0f",
                "fontStyle": "strikethrough"
            }
        },
        {
            "scope": [
                "invalid.illegal"
            ],
            "settings": {
                "foreground": "#b92e0f",
                "fontStyle": "underline"
            }
        }
    ],
    "semanticHighlighting": true,
    "semanticTokenColors": {
        "variable": "#433e38",
        "variable.readonly": "#9f4f00",
        "property": "#465f45",
        "property.readonly": "#9f4f00",
        "function": "#317425",
        "method": "#5c752d",
        "function.defaultLibrary": "#317425",
        "method.defaultLibrary": "#5c752d",
        "class": {
            "foreground": "#257493",
            "fontStyle": "italic"
        },
        "interface": {
            "foreground": "#257493",
            "fontStyle": "italic"
        },
        "type": {
            "foreground": "#257493",
            "fontStyle": "italic"
        },
        "type.defaultLibrary": {
            "foreground": "#257493",
            "fontStyle": "italic"
        },
        "typeParameter": {
            "foreground": "#257493",
            "fontStyle": "italic"
        },
        "enum": {
            "foreground": "#257493",
            "fontStyle": "italic"
        },
        "enumMember": "#3f6ea7",
        "namespace": "#533c1a",
        "keyword": {
            "foreground": "#876718",
            "fontStyle": "bold"
        },
        "parameter": "#554a43",
        "variable.defaultLibrary": "#8f4c00",
        "decorator": {
            "foreground": "#8f4c00",
            "fontStyle": "italic"
        }
    }
}
